crypt_utilities/__init__.py
crypt_utilities/asymmetric.py
crypt_utilities/hashes.py
crypt_utilities/symmetric.py
crypt_utilities-0.0.7.dist-info/LICENSE.txt
crypt_utilities-0.0.7.dist-info/METADATA
crypt_utilities-0.0.7.dist-info/WHEEL
crypt_utilities-0.0.7.dist-info/top_level.txt
crypt_utilities-0.0.7.dist-info/RECORD
