Metadata-Version: 2.1
Name: crypt-utilities
Version: 0.0.7
Summary: An easy and simplified cryptographic utility package (fernet, RSA, hashes...)
Home-page: https://github.com/pgmesa-packages/crypt_utilities
Author: Pablo García Mesa
Author-email: pgmesa.sm@gmail.com
License: UNKNOWN
Platform: UNKNOWN
Classifier: Programming Language :: Python :: 3.7
Classifier: License :: OSI Approved :: MIT License
Classifier: Operating System :: OS Independent
Requires-Python: >=3.7
License-File: LICENSE.txt
Requires-Dist: cffi (==1.15.0)
Requires-Dist: cryptography (==36.0.1)
Requires-Dist: pycparser (==2.21)
